multisig_hmac/__init__.py
multisig_hmac/multisig_hmac.py
tests/__init__.py
tests/test_derived.py
tests/test_stored.py
multisig_hmac-0.2.4.dist-info/LICENSE
multisig_hmac-0.2.4.dist-info/METADATA
multisig_hmac-0.2.4.dist-info/WHEEL
multisig_hmac-0.2.4.dist-info/top_level.txt
multisig_hmac-0.2.4.dist-info/RECORD
