Metadata-Version: 2.1
Name: multisig-hmac
Version: 0.2.4
Summary: multisig HMAC
Home-page: https://github.com/AmalieDue/multisig-hmac-python-version
Author: Amalie Due Jensen
Author-email: amalieduejensen@hotmail.com
License: UNKNOWN
Platform: UNKNOWN
Classifier: Programming Language :: Python :: 3
Classifier: License :: OSI Approved :: ISC License (ISCL)
Classifier: Operating System :: OS Independent
